naan/__about__.py
naan/__init__.py
naan/document.py
naan/filesystem.py
naan/naan.py
naan/queries.py
naan-0.0.4.dist-info/METADATA
naan-0.0.4.dist-info/WHEEL
naan-0.0.4.dist-info/licenses/LICENSE
naan-0.0.4.dist-info/RECORD
