Metadata-Version: 2.3
Name: naan
Version: 0.0.4
Project-URL: Documentation, https://github.com/unknown/naan#readme
Project-URL: Issues, https://github.com/unknown/naan/issues
Project-URL: Source, https://github.com/unknown/naan
Author-email: Massimiliano Pippi <mpippi@gmail.com>
License-Expression: MIT
License-File: LICENSE
Classifier: Development Status :: 4 - Beta
Classifier: Programming Language :: Python
Classifier: Programming Language :: Python :: 3.10
Classifier: Programming Language :: Python :: 3.11
Classifier: Programming Language :: Python :: 3.12
Classifier: Programming Language :: Python :: Implementation :: CPython
Classifier: Programming Language :: Python :: Implementation :: PyPy
Requires-Python: >=3.10
Requires-Dist: duckdb
Requires-Dist: faiss-cpu
Requires-Dist: numpy
